setup.py
py_lava_api/LavaAPI.py
py_lava_api/__init__.py
py_lava_api/enums.py
py_lava_api/models.py
py_lava_api/utils.py
py_lava_api.egg-info/PKG-INFO
py_lava_api.egg-info/SOURCES.txt
py_lava_api.egg-info/dependency_links.txt
py_lava_api.egg-info/requires.txt
py_lava_api.egg-info/top_level.txt
test/__init__.py