Metadata-Version: 2.1
Name: py-lava-api
Version: 1.1.0
Summary: Simple work with lava
Home-page: https://github.com/DephPhascow/py_lava_api
Author: dphascow
Author-email: d.sinisterpsychologist@gmail.com
License: MIT Licence
Keywords: lava
Platform: any
